jk_flexdata/FlexDataSelector.py
jk_flexdata/__init__.py
jk_flexdata/flexdata.py
jk_flexdata-0.2025.3.2.dist-info/WHEEL
jk_flexdata-0.2025.3.2.dist-info/METADATA
jk_flexdata-0.2025.3.2.dist-info/RECORD
