Metadata-Version: 2.1
Name: jk_flexdata
Version: 0.2025.3.2
Summary: This python module provides a special dictionary like data data structure that can be easily used to access and modify values of configurations and settings.
Keywords: dictionary,dict,json,configuration
Author-email: Jürgen Knauth <pubsrc@binary-overflow.de>
Maintainer-email: Jürgen Knauth <pubsrc@binary-overflow.de>
Requires-Python: >=3.8
Classifier: Development Status :: 5 - Production/Stable
Classifier: License :: OSI Approved :: Apache Software License
Classifier: Programming Language :: Python :: 3
